base_consumer/__init__.py
base_consumer/main.py
base_consumer-0.5.dist-info/METADATA
base_consumer-0.5.dist-info/WHEEL
base_consumer-0.5.dist-info/top_level.txt
base_consumer-0.5.dist-info/RECORD
