Metadata-Version: 2.2
Name: base-consumer
Version: 0.5
Requires-Dist: confluent_kafka
Dynamic: description
Dynamic: description-content-type
Dynamic: requires-dist
